{"sandbox_id": "399", "timestamp_str": "2019-08-14T16:09:24.056038Z", "cmd_type": "bash-command", "cmd": "ping 8.8.8.8"}
{"sandbox_id": "399", "timestamp_str": "2019-08-14T16:10:52.015019Z", "cmd_type": "bash-command", "cmd": "host exploit-db.com"}
{"sandbox_id": "399", "timestamp_str": "2019-08-14T16:11:41.805813Z", "cmd_type": "bash-command", "cmd": "host www.exploit-db.com"}
{"sandbox_id": "399", "timestamp_str": "2019-08-14T16:12:09.785136Z", "cmd_type": "bash-command", "cmd": "nano /etc/host"}
{"sandbox_id": "399", "timestamp_str": "2019-08-14T16:12:12.098023Z", "cmd_type": "bash-command", "cmd": "nano /etc/hosts"}
{"sandbox_id": "399", "timestamp_str": "2019-08-14T16:12:41.533591Z", "cmd_type": "bash-command", "cmd": "wget http://exploit-db.com/download/45922"}
{"sandbox_id": "399", "timestamp_str": "2019-08-14T16:12:52.090069Z", "cmd_type": "bash-command", "cmd": "nano /etc/hosts"}
{"sandbox_id": "399", "timestamp_str": "2019-08-14T16:13:07.713616Z", "cmd_type": "bash-command", "cmd": "wget http://exploit-db.com/download/45922"}
{"sandbox_id": "399", "timestamp_str": "2019-08-14T16:13:16.591803Z", "cmd_type": "bash-command", "cmd": "less 45922 "}
{"sandbox_id": "399", "timestamp_str": "2019-08-14T16:13:44.414455Z", "cmd_type": "bash-command", "cmd": "scp 45922 alice@172.18.1.5: "}
{"sandbox_id": "399", "timestamp_str": "2019-08-14T16:13:49.185955Z", "cmd_type": "bash-command", "cmd": "ssh alice@172.18.1.5"}
{"sandbox_id": "399", "timestamp_str": "2019-08-14T16:16:36.913384Z", "cmd_type": "bash-command", "cmd": "ssh alice@172.18.1.5"}
{"sandbox_id": "399", "timestamp_str": "2019-08-14T16:18:09.249448Z", "cmd_type": "bash-command", "cmd": "ssh alice@172.18.1.5"}
{"sandbox_id": "399", "timestamp_str": "2019-08-14T16:21:37.072191Z", "cmd_type": "bash-command", "cmd": "s"}
