{"sandbox_id": "50", "timestamp_str": "2020-07-15T09:59:24.785976+02:00", "cmd_type": "bash-command", "cmd": "git clone htpps://github.com/vulnersCom/nmap-vulners/usr/share/nmap/scripts/vulners"}
{"sandbox_id": "50", "timestamp_str": "2020-07-15T09:59:36.114742+02:00", "cmd_type": "bash-command", "cmd": "git clone https://github.com/vulnersCom/nmap-vulners/usr/share/nmap/scripts/vulners"}
{"sandbox_id": "50", "timestamp_str": "2020-07-15T10:00:17.351289+02:00", "cmd_type": "bash-command", "cmd": "nmap =sV =Pn 172.18.1.5"}
{"sandbox_id": "50", "timestamp_str": "2020-07-15T10:00:28.502150+02:00", "cmd_type": "bash-command", "cmd": "nmap -sV -Pn 172.18.1.5"}
{"sandbox_id": "50", "timestamp_str": "2020-07-15T10:04:01.706179+02:00", "cmd_type": "bash-command", "cmd": "git clone https://github.com/scipag/vulscan scipag_vulscan"}
{"sandbox_id": "50", "timestamp_str": "2020-07-15T10:04:39.226013+02:00", "cmd_type": "bash-command", "cmd": "ln -s `pwd`/scipag_vulscan /usr/share/nmap/scripts/vulscan"}
{"sandbox_id": "50", "timestamp_str": "2020-07-15T10:05:02.263474+02:00", "cmd_type": "bash-command", "cmd": "nmap -sV --script=vulscan/vulscan.nse 172.18.1.5"}
{"sandbox_id": "50", "timestamp_str": "2020-07-15T10:07:24.490301+02:00", "cmd_type": "bash-command", "cmd": "cd /usr/share/nmap/scripts/"}
{"sandbox_id": "50", "timestamp_str": "2020-07-15T10:07:25.848817+02:00", "cmd_type": "bash-command", "cmd": "git clone https://github.com/vulnersCom/nmap-vulners.git"}
{"sandbox_id": "50", "timestamp_str": "2020-07-15T10:07:55.666503+02:00", "cmd_type": "bash-command", "cmd": "nmap --script nmap-vulners -sV 172.18.1.5 -p10000"}
