{"sandbox_id": "130", "timestamp_str": "2019-09-19T10:30:36.203948Z", "cmd_type": "bash-command", "cmd": "nmap 10.0.135.83"}
{"sandbox_id": "130", "timestamp_str": "2019-09-19T10:32:34.441832Z", "cmd_type": "bash-command", "cmd": "nikto -h 10.0.135.83"}
{"sandbox_id": "130", "timestamp_str": "2019-09-19T10:32:57.668033Z", "cmd_type": "bash-command", "cmd": "man libssh"}
{"sandbox_id": "130", "timestamp_str": "2019-09-19T10:33:37.001356Z", "cmd_type": "bash-command", "cmd": "nmap -v 10.0.135.83"}
{"sandbox_id": "130", "timestamp_str": "2019-09-19T10:34:26.527202Z", "cmd_type": "bash-command", "cmd": "libssh"}
{"sandbox_id": "130", "timestamp_str": "2019-09-19T10:36:40.791821Z", "cmd_type": "bash-command", "cmd": "nmap -sV -p22 10.0.135.83"}
{"sandbox_id": "130", "timestamp_str": "2019-09-19T10:38:55.822246Z", "cmd_type": "bash-command", "cmd": "libssh-scanner"}
{"sandbox_id": "130", "timestamp_str": "2019-09-19T10:39:32.957416Z", "cmd_type": "bash-command", "cmd": "cd /"}
{"sandbox_id": "130", "timestamp_str": "2019-09-19T10:39:36.348158Z", "cmd_type": "bash-command", "cmd": "cd ~"}
{"sandbox_id": "130", "timestamp_str": "2019-09-19T10:39:37.609301Z", "cmd_type": "bash-command", "cmd": "ll"}
{"sandbox_id": "130", "timestamp_str": "2019-09-19T10:39:39.365021Z", "cmd_type": "bash-command", "cmd": "ls"}
{"sandbox_id": "130", "timestamp_str": "2019-09-19T10:40:54.882246Z", "cmd_type": "bash-command", "cmd": "find / libsshscan"}
{"sandbox_id": "130", "timestamp_str": "2019-09-19T10:41:50.461873Z", "cmd_type": "bash-command", "cmd": "find / -name \\"}
{"sandbox_id": "130", "timestamp_str": "2019-09-19T10:44:16.581570Z", "cmd_type": "bash-command", "cmd": "nmap -sV -p22 10.0.135.83"}
